{
    "潘妮秘宝_免广告卡_点击商店": {
        "recognition": "TemplateMatch",
        "template": [
            "Panni_free/商店.png"
        ],
        "roi": [
            518,
            613,
            135,
            104
        ],
        "action": "Click",
        "next": [
            "潘妮秘宝_免广告卡_点击秘宝",
            "潘妮秘宝_免广告卡_点击商店"
        ]
    },
    "潘妮秘宝_免广告卡_点击秘宝": {
        "recognition": "TemplateMatch",
        "template": [
            "Panni_free/秘宝.png"
        ],
        "roi": [
            127,
            19,
            914,
            673
        ],
        "action": "Click",
        "next": [
            "潘妮秘宝_免广告卡_普通宝物",
            "潘妮秘宝_免广告卡_点击秘宝"
        ]
    },
    "潘妮秘宝_免广告卡_普通宝物": {
        "recognition": "OCR",
        "expected": [
            "获得"
        ],
        "roi": [
            186,
            590,
            162,
            67
        ],
        "action": "Click",
        "post_wait_freezes": 500,
        "next": [
            "潘妮秘宝_免广告卡_普通宝物_领取",
            "潘妮秘宝_免广告卡_普通宝物_关闭"
        ]
    },
    "潘妮秘宝_免广告卡_普通宝物_领取": {
        "recognition": "OCR",
        "expected": [
            "观看广告"
        ],
        "roi": [
            426,
            544,
            134,
            56
        ],
        "action": "Click",
        "next": [
            "潘妮秘宝_免广告卡_普通宝物_观看广告_点击开启_确定"
        ]
    },
    "潘妮秘宝_免广告卡_普通宝物_观看广告_点击开启_确定": {
        "recognition": "OCR",
        "expected": [
            "确定"
        ],
        "roi": [
            714,
            605,
            90,
            48
        ],
        "action": "Click",
        "next": [
            "潘妮秘宝_免广告卡_普通宝物_关闭"
        ]
    },
    "潘妮秘宝_免广告卡_普通宝物_关闭": {
        "recognition": "TemplateMatch",
        "template": [
            "Panni_free/叉叉.png"
        ],
        "roi": [
            829,
            14,
            106,
            101
        ],
        "action": "Click",
        "next": [
            "免广告卡_潘妮秘宝",
            "潘妮秘宝_免广告卡_普通宝物_关闭",
            "有免广告卡_前置检查"
        ]
    },
}